{
  "apk_file": "3FE070C343EF750E760E8C0ADAFD7A2AFA8BFBB0A4E959456ED18EE0831B1DEA.apk",
  "permissions_list": "android.permission.ACCESS_NETWORK_STATE,android.permission.ACCESS_WIFI_STATE,android.permission.INTERNET,android.permission.RECEIVE_BOOT_COMPLETED,android.permission.WRITE_EXTERNAL_STORAGE,android.permission.WAKE_LOCK,com.google.android.c2dm.permission.RECEIVE,android.permission.READ_EXTERNAL_STORAGE",
  "has_camera": 0,
  "has_gps": 0,
  "has_mic": 0,
  "has_sms": 0,
  "has_overlay": 0,
  "has_boot_completed": 1,
  "is_debuggable": 0,
  "count_activity": 2,
  "count_service": 5,
  "count_receiver": 5,
  "count_provider": 3,
  "count_exported": 2
}
