{
  "apk_file": "40D07C1581B9DE4B98E003EE062326A6339A654C261DD0C0703C0B4A8DA082C7.apk",
  "permissions_list": "android.permission.RECEIVE_BOOT_COMPLETED,android.permission.SCHEDULE_EXACT_ALARM,android.permission.INTERNET,android.permission.ACCESS_NETWORK_STATE,android.permission.ACCESS_COARSE_LOCATION,android.permission.ACCESS_FINE_LOCATION,android.permission.CAMERA,android.permission.READ_EXTERNAL_STORAGE,android.permission.WRITE_EXTERNAL_STORAGE,android.permission.BLUETOOTH,android.permission.BLUETOOTH_ADMIN,android.permission.BLUETOOTH_SCAN,android.permission.BLUETOOTH_ADVERTISE,android.permission.BLUETOOTH_CONNECT,android.permission.FLASHLIGHT,android.permission.NFC,android.permission.FOREGROUND_SERVICE",
  "has_camera": 1,
  "has_gps": 1,
  "has_mic": 0,
  "has_sms": 0,
  "has_overlay": 0,
  "has_boot_completed": 1,
  "is_debuggable": 0,
  "count_activity": 3,
  "count_service": 1,
  "count_receiver": 5,
  "count_provider": 2,
  "count_exported": 1
}
