{
  "apk_file": "F657F3EE3019243CA369DC77487CB57B959B6E06C97C5427C547D4BDC0D3B98F.apk",
  "permissions_list": "android.permission.WRITE_EXTERNAL_STORAGE,android.permission.INTERNET,android.permission.ACCESS_NETWORK_STATE,android.permission.ACCESS_WIFI_STATE,android.permission.WRITE_EXTERNAL_STORAGE,android.permission.FOREGROUND_SERVICE,android.permission.WAKE_LOCK,com.google.android.c2dm.permission.RECEIVE,uk.co.stefsquared.yugioh.permission.C2D_MESSAGE,com.google.android.finsky.permission.BIND_GET_INSTALL_REFERRER_SERVICE,android.permission.READ_EXTERNAL_STORAGE",
  "has_camera": 0,
  "has_gps": 0,
  "has_mic": 0,
  "has_sms": 0,
  "has_overlay": 0,
  "has_boot_completed": 0,
  "is_debuggable": 0,
  "count_activity": 10,
  "count_service": 6,
  "count_receiver": 6,
  "count_provider": 2,
  "count_exported": 3
}
